__init__.py
analysis.py
file_operate.py
hyper.py
modeling.py
ploting.py
preprocess.py
statistic_test.py
utils.py
quickpanda_aidroid-0.0.1.dist-info/METADATA
quickpanda_aidroid-0.0.1.dist-info/WHEEL
quickpanda_aidroid-0.0.1.dist-info/top_level.txt
quickpanda_aidroid-0.0.1.dist-info/RECORD
