Metadata-Version: 2.1
Name: quickpanda-aidroid
Version: 0.0.1
Summary: quick analysis and dataanalysis pipleline 
Home-page: https://github.com/yasuo626/QuickPanda
Author: aidroid
Author-email: Example Author <author@example.com>
Project-URL: Homepage, https://github.com/pypa/sampleproject
Project-URL: Bug Tracker, https://github.com/pypa/sampleproject/issues
Keywords: computer vision
Classifier: Programming Language :: Python :: 3
Classifier: License :: OSI Approved :: MIT License
Classifier: Operating System :: OS Independent
Requires-Python: >=3.6
Requires-Dist: pandas
Requires-Dist: sklearn
Requires-Dist: numpy
